openbim/__main__.py
openbim/convert.py
openbim/csi/__init__.py
openbim/csi/__main__.py
openbim/csi/_section.py
openbim/csi/_shell.py
openbim/csi/bridge.py
openbim/csi/config.py
openbim/csi/handler.py
openbim/csi/link.py
openbim/csi/parse.py
openbim/csi/pattern.py
openbim/csi/point.py
openbim/csi/schema.py
openbim/csi/scratch.py
openbim/csi/tables.py
openbim/csi/utility.py
openbim/csi/_frame/__init__.py
openbim/csi/_frame/section.py
openbim/csi/api/etabs_utilities.py
openbim/csi/api/general_utilities.py
openbim/csi/api/main.py
openbim/csi/api/opensees_postprocessor.py
openbim/csi/api/opensees_utilities.py
openbim/inp/__init__.py
openbim/inp/__main__.py
openbim/inp/model.py
openbim/inp/parser.py
openbim/msh/__init__.py
openbim/msh/element.py
openbim/msh/nodes.py
openbim/msh/utils.py
openbim/msh/viz.py
openbim/msh/examples/example1.py
openbim/msh/examples/example2.py
openbim/msh/examples/example3.py
openbim/msh/examples/example4.py
openbim/msh/examples/example5.py
xbim/__init__.py
xbim/peri.py
xbim/core/__init__.py
xbim/core/convert.py
xbim/frame/shapes/__init__.py
xbim/ifc/__main__.py
xbim/ifc/analysis.py
xbim/ifc/export.py
xbim/ifc/meshing.py
xbim-0.0.0.dist-info/licenses/LICENSE
xbim-0.0.0.dist-info/METADATA
xbim-0.0.0.dist-info/WHEEL
xbim-0.0.0.dist-info/entry_points.txt
xbim-0.0.0.dist-info/top_level.txt
xbim-0.0.0.dist-info/RECORD
